cros_ec_python/__init__.py
cros_ec_python/baseclass.py
cros_ec_python/cros_ec.py
cros_ec_python/exceptions.py
cros_ec_python/commands/__init__.py
cros_ec_python/commands/features.py
cros_ec_python/commands/framework_laptop.py
cros_ec_python/commands/general.py
cros_ec_python/commands/leds.py
cros_ec_python/commands/memmap.py
cros_ec_python/commands/pwm.py
cros_ec_python/commands/thermal.py
cros_ec_python/constants/COMMON.py
cros_ec_python/constants/LPC.py
cros_ec_python/constants/MEMMAP.py
cros_ec_python/constants/__init__.py
cros_ec_python/devices/__init__.py
cros_ec_python/devices/dev.py
cros_ec_python/devices/lpc.py
cros_ec_python/devices/pawnio.py
cros_ec_python/devices/win_fw_ec.py
cros_ec_python/ioports/__init__.py
cros_ec_python/ioports/baseportio.py
cros_ec_python/ioports/devportio.py
cros_ec_python/ioports/freebsdportio.py
cros_ec_python/ioports/winportio.py
cros_ec_python/ioports/x86portio.py
cros_ec_python-0.3.0.dist-info/licenses/LICENCE
cros_ec_python-0.3.0.dist-info/METADATA
cros_ec_python-0.3.0.dist-info/WHEEL
cros_ec_python-0.3.0.dist-info/top_level.txt
cros_ec_python-0.3.0.dist-info/RECORD
