Metadata-Version: 2.4
Name: cros_ec_python
Version: 0.3.0
Summary: A Python library for interacting with a Chrome OS EC.
Author: Steve-Tech
License-Expression: GPL-2.0-or-later
Project-URL: Documentation, https://steve-tech.github.io/CrOS_EC_Python/
Project-URL: Repository, https://github.com/Steve-Tech/CrOS_EC_Python
Project-URL: Issues, https://github.com/Steve-Tech/CrOS_EC_Python/issues
Classifier: Development Status :: 3 - Alpha
Classifier: Intended Audience :: Developers
Classifier: Programming Language :: Python :: 3
Classifier: Operating System :: POSIX :: Linux
Classifier: Operating System :: Microsoft :: Windows
Classifier: Operating System :: POSIX :: BSD :: FreeBSD
Classifier: Topic :: System :: Hardware
Classifier: Topic :: Software Development :: Libraries
Requires-Python: >=3.10
License-File: LICENCE
Provides-Extra: docs
Requires-Dist: pdoc; extra == "docs"
Requires-Dist: portio; extra == "docs"
Provides-Extra: lpc
Requires-Dist: portio; sys_platform == "linux" and extra == "lpc"
Requires-Dist: wmi; sys_platform == "win32" and extra == "lpc"
Dynamic: license-file
